.coveragerc
.travis.yml
AUTHORS.rst
CHANGELOG.rst
LICENSE.txt
README.md
requirements.txt
setup.cfg
setup.py
docs/Makefile
docs/authors.rst
docs/changelog.rst
docs/conf.py
docs/index.rst
docs/license.rst
docs/_static/.gitignore
src/ghrequests/__init__.py
src/ghrequests/requester.py
src/ghrequests.egg-info/PKG-INFO
src/ghrequests.egg-info/SOURCES.txt
src/ghrequests.egg-info/dependency_links.txt
src/ghrequests.egg-info/not-zip-safe
src/ghrequests.egg-info/requires.txt
src/ghrequests.egg-info/top_level.txt
tests/conftest.py
tests/test_functional.py