Metadata-Version: 2.1
Name: ghrequests
Version: 0.0.3
Summary: Python library for massive (but controlled) parallel HTTP calls using requests
Home-page: https://github.com/pappacena/ghrequests/
Author: pappacena
Author-email: pappacena@gmail.com
License: mit
Project-URL: Documentation, https://pyscaffold.org/
Platform: any
Classifier: Development Status :: 4 - Beta
Classifier: Programming Language :: Python
Classifier: Programming Language :: Python :: 2.7
Classifier: Programming Language :: Python :: 3.7
Classifier: Programming Language :: Python :: 3.8
Classifier: Programming Language :: Python :: 3.9
Classifier: Topic :: Internet :: WWW/HTTP
Requires-Python: !=3.0.*,!=3.1.*,!=3.2.*,!=3.3.*,!=3.4.*,!=3.5.*,>=2.7
Provides-Extra: testing
